ldaputils/__init__.py
ldaputils/service.py
ldaputils/utils.py
ldaputils-0.1.11.dist-info/licenses/LICENSE
ldaputils-0.1.11.dist-info/METADATA
ldaputils-0.1.11.dist-info/WHEEL
ldaputils-0.1.11.dist-info/top_level.txt
ldaputils-0.1.11.dist-info/RECORD
