Metadata-Version: 2.4
Name: ldaputils
Version: 0.1.11
Summary: Ldap utils library.
Author: rRR0VrFP
Maintainer: rRR0VrFP
License: MIT
Keywords: ldaputils
Classifier: Development Status :: 5 - Production/Stable
Classifier: Intended Audience :: Developers
Classifier: Topic :: Software Development :: Libraries :: Python Modules
Classifier: License :: OSI Approved :: MIT License
Classifier: Programming Language :: Python :: 3
Classifier: Programming Language :: Python :: 3 :: Only
License-File: LICENSE
Requires-Dist: ldap3>=2.8.1
Requires-Dist: fastutils>=0.36.2
Dynamic: author
Dynamic: classifier
Dynamic: description
Dynamic: description-content-type
Dynamic: keywords
Dynamic: license
Dynamic: license-file
Dynamic: maintainer
Dynamic: requires-dist
Dynamic: summary
